tilty_dashboard/__init__.py
tilty_dashboard/model.py
tilty_dashboard/static/__init__.py
tilty_dashboard/static/dash.css
tilty_dashboard/static/gauge.js
tilty_dashboard/static/logo_50_50.png
tilty_dashboard/static/navbar.js
tilty_dashboard/templates/__init__.py
tilty_dashboard/templates/dashboard_settings.html
tilty_dashboard/templates/device_config.html
tilty_dashboard/templates/index.html
tilty_dashboard/templates/layout.html
tilty_dashboard/templates/logs.html
tilty_dashboard-1.2.0.dist-info/LICENSE
tilty_dashboard-1.2.0.dist-info/METADATA
tilty_dashboard-1.2.0.dist-info/WHEEL
tilty_dashboard-1.2.0.dist-info/top_level.txt
tilty_dashboard-1.2.0.dist-info/RECORD
