Metadata-Version: 2.1
Name: tilty-dashboard
Version: 1.2.0
Summary: A live dashboard for the tilty based on Flask-SocketIO
Home-page: UNKNOWN
Author: Marcus Young
Author-email: 3vilpenguin@gmail.com
License: UNKNOWN
Platform: UNKNOWN
Requires-Dist: Flask (==2.1.0)
Requires-Dist: Jinja2 (==2.11.3)
Requires-Dist: Flask-SocketIO (==5.2.0)
Requires-Dist: Flask-SQLAlchemy (==2.4.4)
Requires-Dist: Werkzeug (==2.1.2)
Requires-Dist: Flask-Bootstrap (==3.3.7)
Requires-Dist: Flask-Cors (==3.0.9)
Requires-Dist: gunicorn (==20.0.4)
Requires-Dist: configobj (==5.0.6)
Requires-Dist: eventlet (==0.33.1)
Requires-Dist: flask-session (==0.3.2)
Requires-Dist: urllib3 (==1.26.5)
